[{"municipio":"SOLIDARIDAD","id_distrito_local":"11","id_distrito_federal":"1","seccion_localidades":"COL. TORRES DE LA PAZ*_*EL CORCHAL*_*FABRICA DE HIELO CRISTALINO DE LA COSTA*_*FRACC MORGANA*_*INV LAS TORRES DE LA VIRGEN DEL CARMEN*_*PARQUE XCARET*_*PLAYA DEL CARMEN*_*RANCHO EL GUADALUPANO","seccion_colonias":"ALDEA SERENA*_*ALLEGRANZA*_*ALTARIA*_*BALI II*_*BOSQUES DE BAMBU RDCIAL*_*CAMPESTRE*_*CLUB VALENIA*_*EJIDAL*_*EL TIGRILLO*_*FORJADORES DEL EJIDO*_*LA ESCONDIDA*_*LA JOYA*_*LA JOYA CAMPESTRE*_*LOS ALMENDROS*_*PALMARA*_*PRIV MARFIL (LA JOYA III)*_*SIN NOMBRE*_*SPECTA*_*THULA RESIDENCIAL*_*VALLE BAMBU RDCIAL","numero":"766","tipo":"urbano","primera_fuerza":"PAN","votos_primera_fuerza":814,"segunda_fuerza":"MORENA","votos_segunda_fuerza":321,"sistema":"MORENA","votos_sistema":321,"votos_can_nreg":"2","votos_nulos":"30","votos_totales":1622,"lista_nominal":"2939","rentabilidad":1301,"rentabilidad_posicion":193,"competividad":-493,"competividad_posicion":201,"semaforo":"rojo","ciudadanos_registrados":"99","acciones_obras":"1","apoyos_programas":"211","funcionarios":"0","militantes":"0","juntas":"0","visitas":"0","caminatas":"0"}]